fastertags/__init__.py
fastertags/_elements.py
fastertags/_gen.py
fastertags/elements.json
fastertags/elements.py
fastertags/headers.py
fastertags/py.typed
fastertags/shorthands.py
fastertags-0.2024.11.dist-info/LICENSE
fastertags-0.2024.11.dist-info/METADATA
fastertags-0.2024.11.dist-info/WHEEL
fastertags-0.2024.11.dist-info/top_level.txt
fastertags-0.2024.11.dist-info/RECORD
