Metadata-Version: 2.1
Name: fastertags
Version: 0.2024.11
Author-email: Julian Bertram <tirednesscankill@warhog.net>
Project-URL: Homepage, https://github.com/scravy/fastertags
Project-URL: Issues, https://github.com/scravy/fastertags/issues
Classifier: Programming Language :: Python :: 3
Classifier: License :: OSI Approved :: MIT License
Classifier: Operating System :: OS Independent
Classifier: Development Status :: 4 - Beta
Classifier: Intended Audience :: Developers
Classifier: Topic :: Internet :: WWW/HTTP :: Dynamic Content
Classifier: Topic :: Internet :: WWW/HTTP :: Site Management
Classifier: Topic :: Software Development :: Libraries
Classifier: Topic :: Software Development :: Code Generators
Classifier: Topic :: Text Processing :: Markup :: HTML
Classifier: Typing :: Typed
Requires-Python: >=3.12
License-File: LICENSE
Provides-Extra: dev
Requires-Dist: beautifulsoup4==4.12.3; extra == "dev"
Requires-Dist: black==24.10.0; extra == "dev"
Requires-Dist: build==1.2.1; extra == "dev"
Requires-Dist: flake8==7.1.1; extra == "dev"
Requires-Dist: html5lib==1.1; extra == "dev"
Requires-Dist: mypy==1.11.2; extra == "dev"
Requires-Dist: pylint==3.3.0; extra == "dev"
Requires-Dist: pytest==8.3.3; extra == "dev"
Requires-Dist: pytest-asyncio==0.24.0; extra == "dev"
Requires-Dist: pytest-random-order==1.1.1; extra == "dev"
Requires-Dist: twine==5.1.1; extra == "dev"
Requires-Dist: urllib3==2.2.3; extra == "dev"
Requires-Dist: wheel==0.44.0; extra == "dev"
